LICENSE
MANIFEST.in
requirements.txt
setup.py
cdpchaosreport/__init__.py
cdpchaosreport/cli.py
cdpchaosreport/control.py
cdpchaosreport/template/header.md
cdpchaosreport/template/index.md
cdpchaosreport/template/index_to_0.12.2.md
cdpchaosreport/template/index_to_0.15.1.md
cdpchaosreport/template/css/main.css
cdpchaosreport/template/css/normalize.min.css
cdpchaosreport/template/js/.DS_Store
cdpchaosreport/template/js/main.js
cdpchaosreport/template/js/vendor/modernizr-2.8.3.min.js
vztcdpchaos_report.egg-info/PKG-INFO
vztcdpchaos_report.egg-info/SOURCES.txt
vztcdpchaos_report.egg-info/dependency_links.txt
vztcdpchaos_report.egg-info/entry_points.txt
vztcdpchaos_report.egg-info/requires.txt
vztcdpchaos_report.egg-info/top_level.txt