Metadata-Version: 1.2
Name: vztcdpchaos-report
Version: 0.2.4
Summary: CDP chaos reporting lib
Home-page: UNKNOWN
Author: vztcdpchaos
Author-email: sucpandu@gmail.com
License: Apache License Version 2.0
Platform: UNKNOWN
Requires-Python: >=3.5.*
